aafragpy/Kafexhiu2014.py
aafragpy/Kamae2006.py
aafragpy/__init__.py
aafragpy/aafrag.py
aafragpy/.ipynb_checkpoints/__init__-checkpoint.py
aafragpy/.ipynb_checkpoints/aafrag-checkpoint.py
aafragpy/Tables/el_Al_p_04
aafragpy/Tables/el_C_p_04
aafragpy/Tables/el_Fe_p_04
aafragpy/Tables/el_He_He_04
aafragpy/Tables/el_He_He_04L
aafragpy/Tables/el_He_p_04
aafragpy/Tables/el_He_p_04L
aafragpy/Tables/el_p_C_04
aafragpy/Tables/el_p_He_04
aafragpy/Tables/el_p_He_04L
aafragpy/Tables/el_p_p_04
aafragpy/Tables/el_p_p_04L
aafragpy/Tables/gam_Al_p_04
aafragpy/Tables/gam_C_p_04
aafragpy/Tables/gam_Fe_p_04
aafragpy/Tables/gam_He_He_04
aafragpy/Tables/gam_He_He_04L
aafragpy/Tables/gam_He_p_04
aafragpy/Tables/gam_He_p_04L
aafragpy/Tables/gam_p_C_04
aafragpy/Tables/gam_p_He_04
aafragpy/Tables/gam_p_He_04L
aafragpy/Tables/gam_p_p_04
aafragpy/Tables/gam_p_p_04L
aafragpy/Tables/nan_Al_p_04
aafragpy/Tables/nan_C_p_04
aafragpy/Tables/nan_Fe_p_04
aafragpy/Tables/nan_He_He_04
aafragpy/Tables/nan_He_He_04L
aafragpy/Tables/nan_He_p_04
aafragpy/Tables/nan_He_p_04L
aafragpy/Tables/nan_p_C_04
aafragpy/Tables/nan_p_He_04
aafragpy/Tables/nan_p_He_04L
aafragpy/Tables/nan_p_p_04
aafragpy/Tables/nan_p_p_04L
aafragpy/Tables/nu_Al_p_04
aafragpy/Tables/nu_C_p_04
aafragpy/Tables/nu_Fe_p_04
aafragpy/Tables/nu_He_He_04
aafragpy/Tables/nu_He_He_04L
aafragpy/Tables/nu_He_p_04
aafragpy/Tables/nu_He_p_04L
aafragpy/Tables/nu_p_C_04
aafragpy/Tables/nu_p_He_04
aafragpy/Tables/nu_p_He_04L
aafragpy/Tables/nu_p_p_04
aafragpy/Tables/nu_p_p_04L
aafragpy/Tables/pap_Al_p_04
aafragpy/Tables/pap_C_p_04
aafragpy/Tables/pap_Fe_p_04
aafragpy/Tables/pap_He_He_04
aafragpy/Tables/pap_He_He_04L
aafragpy/Tables/pap_He_p_04
aafragpy/Tables/pap_He_p_04L
aafragpy/Tables/pap_p_C_04
aafragpy/Tables/pap_p_He_04
aafragpy/Tables/pap_p_He_04L
aafragpy/Tables/pap_p_p_04
aafragpy/Tables/pap_p_p_04L
aafragpy_serkol-0.8.45.dist-info/LICENSE
aafragpy_serkol-0.8.45.dist-info/METADATA
aafragpy_serkol-0.8.45.dist-info/WHEEL
aafragpy_serkol-0.8.45.dist-info/top_level.txt
aafragpy_serkol-0.8.45.dist-info/RECORD
