Metadata-Version: 2.1
Name: aafragpy-serkol
Version: 0.8.45
Summary: Python package for calculation of secondary particle production in nuclear interactions
Home-page: https://github.com/skoldobskiy/aafragpy
Author: Sergey Koldobskiy
Author-email: sakoldobskiy@mephi.ru
License: MIT
Project-URL: Bug Tracker, https://github.com/skoldobskiy/aafragpy/issues
Platform: any
Classifier: Programming Language :: Python :: 3
Classifier: License :: OSI Approved :: MIT License
Classifier: Operating System :: OS Independent
Requires-Python: >=3.6
License-File: LICENSE
